nikola_plugin_docker_driver/__init__.py
nikola_plugin_docker_driver/actions/__init__.py
nikola_plugin_docker_driver/actions/monitor_job.py
nikola_plugin_docker_driver/actions/run_job.py
nikola_plugin_docker_driver/responses/__init__.py
nikola_plugin_docker_driver/responses/monitor_job.py
nikola_plugin_docker_driver/responses/run_job.py
nikola_plugin_docker_driver-0.0.3.dist-info/METADATA
nikola_plugin_docker_driver-0.0.3.dist-info/WHEEL
nikola_plugin_docker_driver-0.0.3.dist-info/top_level.txt
nikola_plugin_docker_driver-0.0.3.dist-info/RECORD
